{"_id": {"$oid": "6475ae470af59419c99f98f2"}, "type": "Fuel Type", "methods": [{"sourceOfEmission": "Blast Furnace Gas", "co2Factor": 274.32, "ch4Factor": 0.022, "n2oFactor": 0.1, "baseUnit": "mmBtu", "source": "EPA", "urlName": "EPA GHG Emission Factors Hub", "sheetName": "Emission Factors Hub", "file": "/upload/ef/EPA-ghg-emission-factors-hub.xlsx", "link": "https://www.epa.gov/system/files/documents/2023-03/ghg-emission-factors-hub.xlsx", "year": 2023, "emissionUnit": "kgCO\u2082", "ch4Unit": "gCH\u2084", "n2oUnit": "gN\u2082O"}, {"sourceOfEmission": "Blast Furnace Gas", "co2Factor": 0.02524, "ch4Factor": 2e-06, "n2oFactor": 9e-06, "baseUnit": "scf", "source": "EPA", "urlName": "EPA GHG Emission Factors Hub", "sheetName": "Emission Factors Hub", "file": "/upload/ef/EPA-ghg-emission-factors-hub.xlsx", "link": "https://www.epa.gov/system/files/documents/2023-03/ghg-emission-factors-hub.xlsx", "year": 2023, "emissionUnit": "kgCO\u2082", "ch4Unit": "gCH\u2084", "n2oUnit": "gN\u2082O"}, {"sourceOfEmission": "Coke Oven Gas", "co2Factor": 46.85, "ch4Factor": 0.48, "n2oFactor": 0.1, "baseUnit": "mmBtu", "source": "EPA", "urlName": "EPA GHG Emission Factors Hub", "sheetName": "Emission Factors Hub", "file": "/upload/ef/EPA-ghg-emission-factors-hub.xlsx", "link": "https://www.epa.gov/system/files/documents/2023-03/ghg-emission-factors-hub.xlsx", "year": 2023, "emissionUnit": "kgCO\u2082", "ch4Unit": "gCH\u2084", "n2oUnit": "gN\u2082O"}, {"sourceOfEmission": "Coke Oven Gas", "co2Factor": 0.02806, "ch4Factor": 0.000288, "n2oFactor": 6e-05, "baseUnit": "scf", "source": "EPA", "urlName": "EPA GHG Emission Factors Hub", "sheetName": "Emission Factors Hub", "file": "/upload/ef/EPA-ghg-emission-factors-hub.xlsx", "link": "https://www.epa.gov/system/files/documents/2023-03/ghg-emission-factors-hub.xlsx", "year": 2023, "emissionUnit": "kgCO\u2082", "ch4Unit": "gCH\u2084", "n2oUnit": "gN\u2082O"}, {"sourceOfEmission": "Fuel Gas", "co2Factor": 59.0, "ch4Factor": 3.0, "n2oFactor": 0.6, "baseUnit": "mmBtu", "source": "EPA", "urlName": "EPA GHG Emission Factors Hub", "sheetName": "Emission Factors Hub", "file": "/upload/ef/EPA-ghg-emission-factors-hub.xlsx", "link": "https://www.epa.gov/system/files/documents/2023-03/ghg-emission-factors-hub.xlsx", "year": 2023, "emissionUnit": "kgCO\u2082", "ch4Unit": "gCH\u2084", "n2oUnit": "gN\u2082O"}, {"sourceOfEmission": "Fuel Gas", "co2Factor": 0.08189, "ch4Factor": 0.004164, "n2oFactor": 0.000833, "baseUnit": "scf", "source": "EPA", "urlName": "EPA GHG Emission Factors Hub", "sheetName": "Emission Factors Hub", "file": "/upload/ef/EPA-ghg-emission-factors-hub.xlsx", "link": "https://www.epa.gov/system/files/documents/2023-03/ghg-emission-factors-hub.xlsx", "year": 2023, "emissionUnit": "kgCO\u2082", "ch4Unit": "gCH\u2084", "n2oUnit": "gN\u2082O"}, {"sourceOfEmission": "Propane Gas", "co2Factor": 61.46, "ch4Factor": 3.0, "n2oFactor": 0.6, "baseUnit": "mmBtu", "source": "EPA", "urlName": "EPA GHG Emission Factors Hub", "sheetName": "Emission Factors Hub", "file": "/upload/ef/EPA-ghg-emission-factors-hub.xlsx", "link": "https://www.epa.gov/system/files/documents/2023-03/ghg-emission-factors-hub.xlsx", "year": 2023, "emissionUnit": "kgCO\u2082", "ch4Unit": "gCH\u2084", "n2oUnit": "gN\u2082O"}, {"sourceOfEmission": "Propane Gas", "co2Factor": 0.15463, "ch4Factor": 0.007548, "n2oFactor": 0.00151, "baseUnit": "scf", "source": "EPA", "urlName": "EPA GHG Emission Factors Hub", "sheetName": "Emission Factors Hub", "file": "/upload/ef/EPA-ghg-emission-factors-hub.xlsx", "link": "https://www.epa.gov/system/files/documents/2023-03/ghg-emission-factors-hub.xlsx", "year": 2023, "emissionUnit": "kgCO\u2082", "ch4Unit": "gCH\u2084", "n2oUnit": "gN\u2082O"}], "scope": "scope1", "typeOfEmission": "Other Fuels - Gaseous", "category": "Stationary Combustion", "categoryKey": "category", "nameKey": "fuelType", "sourceType": "Fuel Type"}